setup.py
madiolahb/__init__.py
madiolahb/__main__.py
madiolahb/acting.py
madiolahb/chardesc.py
madiolahb/core.py
madiolahb/movement.py
madiolahb/timecommands.py
madiolahb.egg-info/PKG-INFO
madiolahb.egg-info/SOURCES.txt
madiolahb.egg-info/dependency_links.txt
madiolahb.egg-info/entry_points.txt
madiolahb.egg-info/requires.txt
madiolahb.egg-info/top_level.txt
madiolahb.egg-info/zip-safe