Metadata-Version: 1.0
Name: madiolahb
Version: 11.12.07
Summary: madiolahb -- Bahloidam laboratory
Home-page: http://madiolahb.code.worldmaker.net
Author: Max Battcher
Author-email: me@worldmaker.net
License: Microsoft Reciprocal License (Ms-RL)
Platform: UNKNOWN
Classifier: Development Status :: 2 - Pre-Alpha
